pyrustaudit/_pyrustaudit.pypy311-pp73-darwin.h
pyrustaudit/_pyrustaudit.pypy311-pp73-darwin.so
pyrustaudit/__init__.py
pyrustaudit/_pyinstaller/hook-pyrustaudit.py
pyrustaudit/_pyinstaller/__init__.py
pyrustaudit-0.0.11.dist-info/RECORD
pyrustaudit-0.0.11.dist-info/WHEEL
pyrustaudit-0.0.11.dist-info/entry_points.txt
pyrustaudit-0.0.11.dist-info/top_level.txt
pyrustaudit-0.0.11.dist-info/METADATA
pyrustaudit-0.0.11.dist-info/licenses/LICENSE
pyrustaudit-0.0.11.data/scripts/get_rust_audit
