Metadata-Version: 2.4
Name: pyrustaudit
Version: 0.0.11
Summary: A utility to extract rust audit  information from rust executable if audit enabled
Home-page: https://github.com/Mikemoore63/pyrustaudit
Author: Mike Moore
Author-email: z_z_zebra@yahoo.com
License: MIT
Classifier: Programming Language :: Python :: 3
Classifier: License :: OSI Approved :: MIT License
Classifier: Operating System :: OS Independent
License-File: LICENSE
Dynamic: license-file
